unisdk/__init__.py
unisdk/__version__.py
unisdk/core.py
unisdk/exception.py
unisdk/response.py
unisdk/sms/__init__.py
unisms-0.0.7.dist-info/LICENSE
unisms-0.0.7.dist-info/METADATA
unisms-0.0.7.dist-info/WHEEL
unisms-0.0.7.dist-info/top_level.txt
unisms-0.0.7.dist-info/RECORD
