Metadata-Version: 2.1
Name: unisms
Version: 0.0.7
Summary: UniSMS SDK for Python.
Home-page: https://github.com/apistd/uni-python-sdk
Author: Acathur
Author-email: i@acathur.com
License: MIT
Platform: UNKNOWN
Classifier: License :: OSI Approved :: MIT License
Classifier: Programming Language :: Python
Classifier: Programming Language :: Python :: 3
Classifier: Programming Language :: Python :: 3.6
Classifier: Programming Language :: Python :: Implementation :: CPython
Classifier: Programming Language :: Python :: Implementation :: PyPy
Requires-Python: >=3.6.0
Requires-Dist: uni-sdk (==0.2.0)
